DeepScence/__init__.py
DeepScence/api.py
DeepScence/io.py
DeepScence/network.py
DeepScence/train.py
DeepScence/data/coreGS_v2.csv
DeepScence-1.0.0.dist-info/METADATA
DeepScence-1.0.0.dist-info/WHEEL
DeepScence-1.0.0.dist-info/top_level.txt
DeepScence-1.0.0.dist-info/RECORD
