Metadata-Version: 2.1
Name: DeepScence
Version: 1.0.0
Summary: single-cell and spatial detection of senescent cells
Home-page: https://github.com/quyilong0402/DeepScence
Author: Anthony Qu
Author-email: anthonyylq@gmail.com
Classifier: Programming Language :: Python :: 3
Classifier: License :: OSI Approved :: MIT License
Classifier: Operating System :: OS Independent
Requires-Python: >=3.6
Requires-Dist: numpy >=1.7
Requires-Dist: torch
Requires-Dist: h5py
Requires-Dist: six >=1.10.0
Requires-Dist: scikit-learn
Requires-Dist: scanpy
Requires-Dist: kopt
Requires-Dist: pandas
